keboola/json_to_csv/__init__.py
keboola/json_to_csv/analyzer.py
keboola/json_to_csv/csv_row.py
keboola/json_to_csv/exceptions.py
keboola/json_to_csv/mapping.py
keboola/json_to_csv/node.py
keboola/json_to_csv/parser.py
keboola/json_to_csv/table.py
keboola/json_to_csv/utils.py
keboola.json_to_csv-0.0.12.dist-info/LICENSE
keboola.json_to_csv-0.0.12.dist-info/METADATA
keboola.json_to_csv-0.0.12.dist-info/WHEEL
keboola.json_to_csv-0.0.12.dist-info/top_level.txt
keboola.json_to_csv-0.0.12.dist-info/RECORD
