Metadata-Version: 2.1
Name: keboola.json-to-csv
Version: 0.0.12
Summary: General utility library for Python applications running in Keboola Connection environment
Home-page: https://github.com/keboola/python-utils
Author: Keboola KDS Team
Author-email: support@keboola.com
Classifier: Programming Language :: Python :: 3
Classifier: License :: OSI Approved :: MIT License
Classifier: Operating System :: OS Independent
Classifier: Intended Audience :: Developers
Classifier: Intended Audience :: Information Technology
Classifier: Intended Audience :: Education
Classifier: Topic :: Software Development :: Libraries
Classifier: Topic :: Software Development :: Libraries :: Python Modules
Requires-Python: >=3.7
License-File: LICENSE
